{"skeleton":{"hash":"v/HUElvzgLE1ZGTQzjBClcZFzFo","spine":"2.1.27","width":1559,"height":723.93,"images":""},"bones":[{"name":"root"},{"name":"bgg1","parent":"root"},{"name":"bone17","parent":"root","x":-20.93,"y":11.43},{"name":"shang","parent":"root"},{"name":"xia","parent":"root"},{"name":"bg1","parent":"bgg1","x":390,"y":-296.05,"scaleY":2.629},{"name":"bg2","parent":"bgg1","x":-390,"y":-296.05,"scaleY":2.629},{"name":"bg3","parent":"bgg1","x":-390,"y":294.79,"scaleY":-2.63},{"name":"bg4","parent":"bgg1","x":390,"y":294.8,"scaleY":-2.63},{"name":"bone","parent":"shang","x":686.2,"y":305.65},{"name":"bone10","parent":"xia","x":472.06,"y":-305.73,"scaleY":-1},{"name":"bone11","parent":"xia","x":284.81,"y":-305.73,"scaleY":-1},{"name":"bone12","parent":"xia","x":94.01,"y":-305.73,"scaleY":-1},{"name":"bone13","parent":"xia","x":-98.17,"y":-305.73,"scaleY":-1},{"name":"bone14","parent":"xia","x":-285.35,"y":-305.73,"scaleY":-1},{"name":"bone15","parent":"xia","x":-473.94,"y":-305.73,"scaleY":-1},{"name":"bone16","parent":"xia","x":-674.81,"y":-305.73,"scaleX":1.116,"scaleY":-1},{"name":"bone2","parent":"shang","x":485.85,"y":305.65,"scaleX":-1},{"name":"bone3","parent":"shang","x":289.91,"y":306.46},{"name":"bone4","parent":"shang","x":89.94,"y":306.46},{"name":"bone5","parent":"shang","x":-102.53,"y":306.46},{"name":"bone6","parent":"shang","x":-293.2,"y":306.46},{"name":"bone7","parent":"shang","x":-484.7,"y":306.46},{"name":"bone8","parent":"shang","x":-678.09,"y":306.46},{"name":"bone9","parent":"xia","x":671.81,"y":-305.73,"scaleX":1.1,"scaleY":-1}],"slots":[{"name":"bgkong","bone":"root"},{"name":"bg1212","bone":"bone17"},{"name":"bgg_00","bone":"bg1"},{"name":"bgg_2","bone":"bg4"},{"name":"bgg_0","bone":"bg2"},{"name":"bgg_1","bone":"bg3"},{"name":"lizi","bone":"bone"},{"name":"lizi9","bone":"bone9"},{"name":"lizi10","bone":"bone10"},{"name":"lizi11","bone":"bone11"},{"name":"lizi12","bone":"bone12"},{"name":"lizi13","bone":"bone13"},{"name":"lizi14","bone":"bone14"},{"name":"lizi15","bone":"bone15"},{"name":"lizi16","bone":"bone16"},{"name":"lizi2","bone":"bone2"},{"name":"lizi3","bone":"bone3"},{"name":"lizi5","bone":"bone5"},{"name":"lizi7","bone":"bone7"},{"name":"lizi4","bone":"bone4"},{"name":"lizi6","bone":"bone6"},{"name":"lizi8","bone":"bone8"}],"skins":{"default":{"bgg_0":{"bgg_00":{"scaleY":1.261,"width":780,"height":40}},"bgg_00":{"bgg_00":{"scaleY":1.261,"width":780,"height":40}},"bgg_1":{"bgg_00":{"scaleY":1.261,"width":780,"height":40}},"bgg_2":{"bgg_00":{"scaleY":1.261,"width":780,"height":40}},"lizi":{"lizi_00":{"width":200,"height":110},"lizi_01":{"width":200,"height":110},"lizi_02":{"width":200,"height":110},"lizi_03":{"width":200,"height":110},"lizi_04":{"width":200,"height":110},"lizi_05":{"width":200,"height":110},"lizi_06":{"width":200,"height":110},"lizi_07":{"width":200,"height":110},"lizi_08":{"width":200,"height":110},"lizi_09":{"width":200,"height":110},"lizi_10":{"width":200,"height":110},"lizi_11":{"width":200,"height":110},"lizi_12":{"width":200,"height":110},"lizi_13":{"width":200,"height":110},"lizi_14":{"width":200,"height":110},"lizi_15":{"width":200,"height":110},"lizi_16":{"width":200,"height":110},"lizi_17":{"width":200,"height":110},"lizi_18":{"width":200,"height":110},"lizi_19":{"width":200,"height":110},"lizi_20":{"width":200,"height":110},"lizi_21":{"width":200,"height":110},"lizi_22":{"width":200,"height":110},"lizi_23":{"width":200,"height":110},"lizi_24":{"width":200,"height":110},"lizi_25":{"width":200,"height":110},"lizi_26":{"width":200,"height":110},"lizi_27":{"width":200,"height":110},"lizi_28":{"width":200,"height":110},"lizi_29":{"width":200,"height":110}},"lizi10":{"lizi_00":{"width":200,"height":110},"lizi_01":{"width":200,"height":110},"lizi_02":{"width":200,"height":110},"lizi_03":{"width":200,"height":110},"lizi_04":{"width":200,"height":110},"lizi_05":{"width":200,"height":110},"lizi_06":{"width":200,"height":110},"lizi_07":{"width":200,"height":110},"lizi_08":{"width":200,"height":110},"lizi_09":{"width":200,"height":110},"lizi_10":{"width":200,"height":110},"lizi_11":{"width":200,"height":110},"lizi_12":{"width":200,"height":110},"lizi_13":{"width":200,"height":110},"lizi_14":{"width":200,"height":110},"lizi_15":{"width":200,"height":110},"lizi_16":{"width":200,"height":110},"lizi_17":{"width":200,"height":110},"lizi_18":{"width":200,"height":110},"lizi_19":{"width":200,"height":110},"lizi_20":{"width":200,"height":110},"lizi_21":{"width":200,"height":110},"lizi_22":{"width":200,"height":110},"lizi_23":{"width":200,"height":110},"lizi_24":{"width":200,"height":110},"lizi_25":{"width":200,"height":110},"lizi_26":{"width":200,"height":110},"lizi_27":{"width":200,"height":110},"lizi_28":{"width":200,"height":110},"lizi_29":{"width":200,"height":110}},"lizi11":{"lizi_00":{"width":200,"height":110},"lizi_01":{"width":200,"height":110},"lizi_02":{"width":200,"height":110},"lizi_03":{"width":200,"height":110},"lizi_04":{"width":200,"height":110},"lizi_05":{"width":200,"height":110},"lizi_06":{"width":200,"height":110},"lizi_07":{"width":200,"height":110},"lizi_08":{"width":200,"height":110},"lizi_09":{"width":200,"height":110},"lizi_10":{"width":200,"height":110},"lizi_11":{"width":200,"height":110},"lizi_12":{"width":200,"height":110},"lizi_13":{"width":200,"height":110},"lizi_14":{"width":200,"height":110},"lizi_15":{"width":200,"height":110},"lizi_16":{"width":200,"height":110},"lizi_17":{"width":200,"height":110},"lizi_18":{"width":200,"height":110},"lizi_19":{"width":200,"height":110},"lizi_20":{"width":200,"height":110},"lizi_21":{"width":200,"height":110},"lizi_22":{"width":200,"height":110},"lizi_23":{"width":200,"height":110},"lizi_24":{"width":200,"height":110},"lizi_25":{"width":200,"height":110},"lizi_26":{"width":200,"height":110},"lizi_27":{"width":200,"height":110},"lizi_28":{"width":200,"height":110},"lizi_29":{"width":200,"height":110}},"lizi12":{"lizi_00":{"width":200,"height":110},"lizi_01":{"width":200,"height":110},"lizi_02":{"width":200,"height":110},"lizi_03":{"width":200,"height":110},"lizi_04":{"width":200,"height":110},"lizi_05":{"width":200,"height":110},"lizi_06":{"width":200,"height":110},"lizi_07":{"width":200,"height":110},"lizi_08":{"width":200,"height":110},"lizi_09":{"width":200,"height":110},"lizi_10":{"width":200,"height":110},"lizi_11":{"width":200,"height":110},"lizi_12":{"width":200,"height":110},"lizi_13":{"width":200,"height":110},"lizi_14":{"width":200,"height":110},"lizi_15":{"width":200,"height":110},"lizi_16":{"width":200,"height":110},"lizi_17":{"width":200,"height":110},"lizi_18":{"width":200,"height":110},"lizi_19":{"width":200,"height":110},"lizi_20":{"width":200,"height":110},"lizi_21":{"width":200,"height":110},"lizi_22":{"width":200,"height":110},"lizi_23":{"width":200,"height":110},"lizi_24":{"width":200,"height":110},"lizi_25":{"width":200,"height":110},"lizi_26":{"width":200,"height":110},"lizi_27":{"width":200,"height":110},"lizi_28":{"width":200,"height":110},"lizi_29":{"width":200,"height":110}},"lizi13":{"lizi_00":{"width":200,"height":110},"lizi_01":{"width":200,"height":110},"lizi_02":{"width":200,"height":110},"lizi_03":{"width":200,"height":110},"lizi_04":{"width":200,"height":110},"lizi_05":{"width":200,"height":110},"lizi_06":{"width":200,"height":110},"lizi_07":{"width":200,"height":110},"lizi_08":{"width":200,"height":110},"lizi_09":{"width":200,"height":110},"lizi_10":{"width":200,"height":110},"lizi_11":{"width":200,"height":110},"lizi_12":{"width":200,"height":110},"lizi_13":{"width":200,"height":110},"lizi_14":{"width":200,"height":110},"lizi_15":{"width":200,"height":110},"lizi_16":{"width":200,"height":110},"lizi_17":{"width":200,"height":110},"lizi_18":{"width":200,"height":110},"lizi_19":{"width":200,"height":110},"lizi_20":{"width":200,"height":110},"lizi_21":{"width":200,"height":110},"lizi_22":{"width":200,"height":110},"lizi_23":{"width":200,"height":110},"lizi_24":{"width":200,"height":110},"lizi_25":{"width":200,"height":110},"lizi_26":{"width":200,"height":110},"lizi_27":{"width":200,"height":110},"lizi_28":{"width":200,"height":110},"lizi_29":{"width":200,"height":110}},"lizi14":{"lizi_00":{"width":200,"height":110},"lizi_01":{"width":200,"height":110},"lizi_02":{"width":200,"height":110},"lizi_03":{"width":200,"height":110},"lizi_04":{"width":200,"height":110},"lizi_05":{"width":200,"height":110},"lizi_06":{"width":200,"height":110},"lizi_07":{"width":200,"height":110},"lizi_08":{"width":200,"height":110},"lizi_09":{"width":200,"height":110},"lizi_10":{"width":200,"height":110},"lizi_11":{"width":200,"height":110},"lizi_12":{"width":200,"height":110},"lizi_13":{"width":200,"height":110},"lizi_14":{"width":200,"height":110},"lizi_15":{"width":200,"height":110},"lizi_16":{"width":200,"height":110},"lizi_17":{"width":200,"height":110},"lizi_18":{"width":200,"height":110},"lizi_19":{"width":200,"height":110},"lizi_20":{"width":200,"height":110},"lizi_21":{"width":200,"height":110},"lizi_22":{"width":200,"height":110},"lizi_23":{"width":200,"height":110},"lizi_24":{"width":200,"height":110},"lizi_25":{"width":200,"height":110},"lizi_26":{"width":200,"height":110},"lizi_27":{"width":200,"height":110},"lizi_28":{"width":200,"height":110},"lizi_29":{"width":200,"height":110}},"lizi15":{"lizi_00":{"width":200,"height":110},"lizi_01":{"width":200,"height":110},"lizi_02":{"width":200,"height":110},"lizi_03":{"width":200,"height":110},"lizi_04":{"width":200,"height":110},"lizi_05":{"width":200,"height":110},"lizi_06":{"width":200,"height":110},"lizi_07":{"width":200,"height":110},"lizi_08":{"width":200,"height":110},"lizi_09":{"width":200,"height":110},"lizi_10":{"width":200,"height":110},"lizi_11":{"width":200,"height":110},"lizi_12":{"width":200,"height":110},"lizi_13":{"width":200,"height":110},"lizi_14":{"width":200,"height":110},"lizi_15":{"width":200,"height":110},"lizi_16":{"width":200,"height":110},"lizi_17":{"width":200,"height":110},"lizi_18":{"width":200,"height":110},"lizi_19":{"width":200,"height":110},"lizi_20":{"width":200,"height":110},"lizi_21":{"width":200,"height":110},"lizi_22":{"width":200,"height":110},"lizi_23":{"width":200,"height":110},"lizi_24":{"width":200,"height":110},"lizi_25":{"width":200,"height":110},"lizi_26":{"width":200,"height":110},"lizi_27":{"width":200,"height":110},"lizi_28":{"width":200,"height":110},"lizi_29":{"width":200,"height":110}},"lizi16":{"lizi_00":{"width":200,"height":110},"lizi_01":{"width":200,"height":110},"lizi_02":{"width":200,"height":110},"lizi_03":{"width":200,"height":110},"lizi_04":{"width":200,"height":110},"lizi_05":{"width":200,"height":110},"lizi_06":{"width":200,"height":110},"lizi_07":{"width":200,"height":110},"lizi_08":{"width":200,"height":110},"lizi_09":{"width":200,"height":110},"lizi_10":{"width":200,"height":110},"lizi_11":{"width":200,"height":110},"lizi_12":{"width":200,"height":110},"lizi_13":{"width":200,"height":110},"lizi_14":{"width":200,"height":110},"lizi_15":{"width":200,"height":110},"lizi_16":{"width":200,"height":110},"lizi_17":{"width":200,"height":110},"lizi_18":{"width":200,"height":110},"lizi_19":{"width":200,"height":110},"lizi_20":{"width":200,"height":110},"lizi_21":{"width":200,"height":110},"lizi_22":{"width":200,"height":110},"lizi_23":{"width":200,"height":110},"lizi_24":{"width":200,"height":110},"lizi_25":{"width":200,"height":110},"lizi_26":{"width":200,"height":110},"lizi_27":{"width":200,"height":110},"lizi_28":{"width":200,"height":110},"lizi_29":{"width":200,"height":110}},"lizi2":{"lizi_00":{"width":200,"height":110},"lizi_01":{"width":200,"height":110},"lizi_02":{"width":200,"height":110},"lizi_03":{"width":200,"height":110},"lizi_04":{"width":200,"height":110},"lizi_05":{"width":200,"height":110},"lizi_06":{"width":200,"height":110},"lizi_07":{"width":200,"height":110},"lizi_08":{"width":200,"height":110},"lizi_09":{"width":200,"height":110},"lizi_10":{"width":200,"height":110},"lizi_11":{"width":200,"height":110},"lizi_12":{"width":200,"height":110},"lizi_13":{"width":200,"height":110},"lizi_14":{"width":200,"height":110},"lizi_15":{"width":200,"height":110},"lizi_16":{"width":200,"height":110},"lizi_17":{"width":200,"height":110},"lizi_18":{"width":200,"height":110},"lizi_19":{"width":200,"height":110},"lizi_20":{"width":200,"height":110},"lizi_21":{"width":200,"height":110},"lizi_22":{"width":200,"height":110},"lizi_23":{"width":200,"height":110},"lizi_24":{"width":200,"height":110},"lizi_25":{"width":200,"height":110},"lizi_26":{"width":200,"height":110},"lizi_27":{"width":200,"height":110},"lizi_28":{"width":200,"height":110},"lizi_29":{"width":200,"height":110}},"lizi3":{"lizi_00":{"width":200,"height":110},"lizi_01":{"width":200,"height":110},"lizi_02":{"width":200,"height":110},"lizi_03":{"width":200,"height":110},"lizi_04":{"width":200,"height":110},"lizi_05":{"width":200,"height":110},"lizi_06":{"width":200,"height":110},"lizi_07":{"width":200,"height":110},"lizi_08":{"width":200,"height":110},"lizi_09":{"width":200,"height":110},"lizi_10":{"width":200,"height":110},"lizi_11":{"width":200,"height":110},"lizi_12":{"width":200,"height":110},"lizi_13":{"width":200,"height":110},"lizi_14":{"width":200,"height":110},"lizi_15":{"width":200,"height":110},"lizi_16":{"width":200,"height":110},"lizi_17":{"width":200,"height":110},"lizi_18":{"width":200,"height":110},"lizi_19":{"width":200,"height":110},"lizi_20":{"width":200,"height":110},"lizi_21":{"width":200,"height":110},"lizi_22":{"width":200,"height":110},"lizi_23":{"width":200,"height":110},"lizi_24":{"width":200,"height":110},"lizi_25":{"width":200,"height":110},"lizi_26":{"width":200,"height":110},"lizi_27":{"width":200,"height":110},"lizi_28":{"width":200,"height":110},"lizi_29":{"width":200,"height":110}},"lizi4":{"lizi_00":{"width":200,"height":110},"lizi_01":{"width":200,"height":110},"lizi_02":{"width":200,"height":110},"lizi_03":{"width":200,"height":110},"lizi_04":{"width":200,"height":110},"lizi_05":{"width":200,"height":110},"lizi_06":{"width":200,"height":110},"lizi_07":{"width":200,"height":110},"lizi_08":{"width":200,"height":110},"lizi_09":{"width":200,"height":110},"lizi_10":{"width":200,"height":110},"lizi_11":{"width":200,"height":110},"lizi_12":{"width":200,"height":110},"lizi_13":{"width":200,"height":110},"lizi_14":{"width":200,"height":110},"lizi_15":{"width":200,"height":110},"lizi_16":{"width":200,"height":110},"lizi_17":{"width":200,"height":110},"lizi_18":{"width":200,"height":110},"lizi_19":{"width":200,"height":110},"lizi_20":{"width":200,"height":110},"lizi_21":{"width":200,"height":110},"lizi_22":{"width":200,"height":110},"lizi_23":{"width":200,"height":110},"lizi_24":{"width":200,"height":110},"lizi_25":{"width":200,"height":110},"lizi_26":{"width":200,"height":110},"lizi_27":{"width":200,"height":110},"lizi_28":{"width":200,"height":110},"lizi_29":{"width":200,"height":110}},"lizi5":{"lizi_00":{"width":200,"height":110},"lizi_01":{"width":200,"height":110},"lizi_02":{"width":200,"height":110},"lizi_03":{"width":200,"height":110},"lizi_04":{"width":200,"height":110},"lizi_05":{"width":200,"height":110},"lizi_06":{"width":200,"height":110},"lizi_07":{"width":200,"height":110},"lizi_08":{"width":200,"height":110},"lizi_09":{"width":200,"height":110},"lizi_10":{"width":200,"height":110},"lizi_11":{"width":200,"height":110},"lizi_12":{"width":200,"height":110},"lizi_13":{"width":200,"height":110},"lizi_14":{"width":200,"height":110},"lizi_15":{"width":200,"height":110},"lizi_16":{"width":200,"height":110},"lizi_17":{"width":200,"height":110},"lizi_18":{"width":200,"height":110},"lizi_19":{"width":200,"height":110},"lizi_20":{"width":200,"height":110},"lizi_21":{"width":200,"height":110},"lizi_22":{"width":200,"height":110},"lizi_23":{"width":200,"height":110},"lizi_24":{"width":200,"height":110},"lizi_25":{"width":200,"height":110},"lizi_26":{"width":200,"height":110},"lizi_27":{"width":200,"height":110},"lizi_28":{"width":200,"height":110},"lizi_29":{"width":200,"height":110}},"lizi6":{"lizi_00":{"width":200,"height":110},"lizi_01":{"width":200,"height":110},"lizi_02":{"width":200,"height":110},"lizi_03":{"width":200,"height":110},"lizi_04":{"width":200,"height":110},"lizi_05":{"width":200,"height":110},"lizi_06":{"width":200,"height":110},"lizi_07":{"width":200,"height":110},"lizi_08":{"width":200,"height":110},"lizi_09":{"width":200,"height":110},"lizi_10":{"width":200,"height":110},"lizi_11":{"width":200,"height":110},"lizi_12":{"width":200,"height":110},"lizi_13":{"width":200,"height":110},"lizi_14":{"width":200,"height":110},"lizi_15":{"width":200,"height":110},"lizi_16":{"width":200,"height":110},"lizi_17":{"width":200,"height":110},"lizi_18":{"width":200,"height":110},"lizi_19":{"width":200,"height":110},"lizi_20":{"width":200,"height":110},"lizi_21":{"width":200,"height":110},"lizi_22":{"width":200,"height":110},"lizi_23":{"width":200,"height":110},"lizi_24":{"width":200,"height":110},"lizi_25":{"width":200,"height":110},"lizi_26":{"width":200,"height":110},"lizi_27":{"width":200,"height":110},"lizi_28":{"width":200,"height":110},"lizi_29":{"width":200,"height":110}},"lizi7":{"lizi_00":{"width":200,"height":110},"lizi_01":{"width":200,"height":110},"lizi_02":{"width":200,"height":110},"lizi_03":{"width":200,"height":110},"lizi_04":{"width":200,"height":110},"lizi_05":{"width":200,"height":110},"lizi_06":{"width":200,"height":110},"lizi_07":{"width":200,"height":110},"lizi_08":{"width":200,"height":110},"lizi_09":{"width":200,"height":110},"lizi_10":{"width":200,"height":110},"lizi_11":{"width":200,"height":110},"lizi_12":{"width":200,"height":110},"lizi_13":{"width":200,"height":110},"lizi_14":{"width":200,"height":110},"lizi_15":{"width":200,"height":110},"lizi_16":{"width":200,"height":110},"lizi_17":{"width":200,"height":110},"lizi_18":{"width":200,"height":110},"lizi_19":{"width":200,"height":110},"lizi_20":{"width":200,"height":110},"lizi_21":{"width":200,"height":110},"lizi_22":{"width":200,"height":110},"lizi_23":{"width":200,"height":110},"lizi_24":{"width":200,"height":110},"lizi_25":{"width":200,"height":110},"lizi_26":{"width":200,"height":110},"lizi_27":{"width":200,"height":110},"lizi_28":{"width":200,"height":110},"lizi_29":{"width":200,"height":110}},"lizi8":{"lizi_00":{"width":200,"height":110},"lizi_01":{"width":200,"height":110},"lizi_02":{"width":200,"height":110},"lizi_03":{"width":200,"height":110},"lizi_04":{"width":200,"height":110},"lizi_05":{"width":200,"height":110},"lizi_06":{"width":200,"height":110},"lizi_07":{"width":200,"height":110},"lizi_08":{"width":200,"height":110},"lizi_09":{"width":200,"height":110},"lizi_10":{"width":200,"height":110},"lizi_11":{"width":200,"height":110},"lizi_12":{"width":200,"height":110},"lizi_13":{"width":200,"height":110},"lizi_14":{"width":200,"height":110},"lizi_15":{"width":200,"height":110},"lizi_16":{"width":200,"height":110},"lizi_17":{"width":200,"height":110},"lizi_18":{"width":200,"height":110},"lizi_19":{"width":200,"height":110},"lizi_20":{"width":200,"height":110},"lizi_21":{"width":200,"height":110},"lizi_22":{"width":200,"height":110},"lizi_23":{"width":200,"height":110},"lizi_24":{"width":200,"height":110},"lizi_25":{"width":200,"height":110},"lizi_26":{"width":200,"height":110},"lizi_27":{"width":200,"height":110},"lizi_28":{"width":200,"height":110},"lizi_29":{"width":200,"height":110}},"lizi9":{"lizi_00":{"width":200,"height":110},"lizi_01":{"width":200,"height":110},"lizi_02":{"width":200,"height":110},"lizi_03":{"width":200,"height":110},"lizi_04":{"width":200,"height":110},"lizi_05":{"width":200,"height":110},"lizi_06":{"width":200,"height":110},"lizi_07":{"width":200,"height":110},"lizi_08":{"width":200,"height":110},"lizi_09":{"width":200,"height":110},"lizi_10":{"width":200,"height":110},"lizi_11":{"width":200,"height":110},"lizi_12":{"width":200,"height":110},"lizi_13":{"width":200,"height":110},"lizi_14":{"width":200,"height":110},"lizi_15":{"width":200,"height":110},"lizi_16":{"width":200,"height":110},"lizi_17":{"width":200,"height":110},"lizi_18":{"width":200,"height":110},"lizi_19":{"width":200,"height":110},"lizi_20":{"width":200,"height":110},"lizi_21":{"width":200,"height":110},"lizi_22":{"width":200,"height":110},"lizi_23":{"width":200,"height":110},"lizi_24":{"width":200,"height":110},"lizi_25":{"width":200,"height":110},"lizi_26":{"width":200,"height":110},"lizi_27":{"width":200,"height":110},"lizi_28":{"width":200,"height":110},"lizi_29":{"width":200,"height":110}}}},"animations":{"mianfeitexiao":{"slots":{"bgg_00":{"attachment":[{"time":0,"name":null}],"color":[{"time":0,"color":"122b5776"}]},"bgg_0":{"attachment":[{"time":0,"name":null}],"color":[{"time":0,"color":"122b5776"}]},"bgg_1":{"attachment":[{"time":0,"name":null}],"color":[{"time":0,"color":"122b5776"}]},"bgg_2":{"attachment":[{"time":0,"name":null}],"color":[{"time":0,"color":"122b5776"}]},"lizi":{"attachment":[{"time":0,"name":"lizi_00"},{"time":0.0333,"name":"lizi_01"},{"time":0.0666,"name":"lizi_02"},{"time":0.1,"name":"lizi_03"},{"time":0.1333,"name":"lizi_04"},{"time":0.1666,"name":"lizi_05"},{"time":0.2,"name":"lizi_06"},{"time":0.2333,"name":"lizi_07"},{"time":0.2666,"name":"lizi_08"},{"time":0.3,"name":"lizi_09"},{"time":0.3333,"name":"lizi_10"},{"time":0.3666,"name":"lizi_11"},{"time":0.4,"name":"lizi_12"},{"time":0.4333,"name":"lizi_13"},{"time":0.4666,"name":"lizi_14"},{"time":0.5,"name":"lizi_15"},{"time":0.5333,"name":"lizi_16"},{"time":0.5666,"name":"lizi_17"},{"time":0.6,"name":"lizi_18"},{"time":0.6333,"name":"lizi_19"},{"time":0.6666,"name":"lizi_20"},{"time":0.7,"name":"lizi_21"},{"time":0.7333,"name":"lizi_22"},{"time":0.7666,"name":"lizi_23"},{"time":0.8,"name":"lizi_24"},{"time":0.8333,"name":"lizi_25"},{"time":0.8666,"name":"lizi_26"},{"time":0.9,"name":"lizi_27"},{"time":0.9333,"name":"lizi_28"},{"time":0.9666,"name":"lizi_29"}]},"lizi2":{"attachment":[{"time":0,"name":"lizi_00"},{"time":0.0333,"name":"lizi_01"},{"time":0.0666,"name":"lizi_02"},{"time":0.1,"name":"lizi_03"},{"time":0.1333,"name":"lizi_04"},{"time":0.1666,"name":"lizi_05"},{"time":0.2,"name":"lizi_06"},{"time":0.2333,"name":"lizi_07"},{"time":0.2666,"name":"lizi_08"},{"time":0.3,"name":"lizi_09"},{"time":0.3333,"name":"lizi_10"},{"time":0.3666,"name":"lizi_11"},{"time":0.4,"name":"lizi_12"},{"time":0.4333,"name":"lizi_13"},{"time":0.4666,"name":"lizi_14"},{"time":0.5,"name":"lizi_15"},{"time":0.5333,"name":"lizi_16"},{"time":0.5666,"name":"lizi_17"},{"time":0.6,"name":"lizi_18"},{"time":0.6333,"name":"lizi_19"},{"time":0.6666,"name":"lizi_20"},{"time":0.7,"name":"lizi_21"},{"time":0.7333,"name":"lizi_22"},{"time":0.7666,"name":"lizi_23"},{"time":0.8,"name":"lizi_24"},{"time":0.8333,"name":"lizi_25"},{"time":0.8666,"name":"lizi_26"},{"time":0.9,"name":"lizi_27"},{"time":0.9333,"name":"lizi_28"},{"time":0.9666,"name":"lizi_29"}]},"lizi3":{"attachment":[{"time":0,"name":"lizi_00"},{"time":0.0333,"name":"lizi_01"},{"time":0.0666,"name":"lizi_02"},{"time":0.1,"name":"lizi_03"},{"time":0.1333,"name":"lizi_04"},{"time":0.1666,"name":"lizi_05"},{"time":0.2,"name":"lizi_06"},{"time":0.2333,"name":"lizi_07"},{"time":0.2666,"name":"lizi_08"},{"time":0.3,"name":"lizi_09"},{"time":0.3333,"name":"lizi_10"},{"time":0.3666,"name":"lizi_11"},{"time":0.4,"name":"lizi_12"},{"time":0.4333,"name":"lizi_13"},{"time":0.4666,"name":"lizi_14"},{"time":0.5,"name":"lizi_15"},{"time":0.5333,"name":"lizi_16"},{"time":0.5666,"name":"lizi_17"},{"time":0.6,"name":"lizi_18"},{"time":0.6333,"name":"lizi_19"},{"time":0.6666,"name":"lizi_20"},{"time":0.7,"name":"lizi_21"},{"time":0.7333,"name":"lizi_22"},{"time":0.7666,"name":"lizi_23"},{"time":0.8,"name":"lizi_24"},{"time":0.8333,"name":"lizi_25"},{"time":0.8666,"name":"lizi_26"},{"time":0.9,"name":"lizi_27"},{"time":0.9333,"name":"lizi_28"},{"time":0.9666,"name":"lizi_29"}]},"lizi4":{"attachment":[{"time":0,"name":"lizi_00"},{"time":0.0333,"name":"lizi_01"},{"time":0.0666,"name":"lizi_02"},{"time":0.1,"name":"lizi_03"},{"time":0.1333,"name":"lizi_04"},{"time":0.1666,"name":"lizi_05"},{"time":0.2,"name":"lizi_06"},{"time":0.2333,"name":"lizi_07"},{"time":0.2666,"name":"lizi_08"},{"time":0.3,"name":"lizi_09"},{"time":0.3333,"name":"lizi_10"},{"time":0.3666,"name":"lizi_11"},{"time":0.4,"name":"lizi_12"},{"time":0.4333,"name":"lizi_13"},{"time":0.4666,"name":"lizi_14"},{"time":0.5,"name":"lizi_15"},{"time":0.5333,"name":"lizi_16"},{"time":0.5666,"name":"lizi_17"},{"time":0.6,"name":"lizi_18"},{"time":0.6333,"name":"lizi_19"},{"time":0.6666,"name":"lizi_20"},{"time":0.7,"name":"lizi_21"},{"time":0.7333,"name":"lizi_22"},{"time":0.7666,"name":"lizi_23"},{"time":0.8,"name":"lizi_24"},{"time":0.8333,"name":"lizi_25"},{"time":0.8666,"name":"lizi_26"},{"time":0.9,"name":"lizi_27"},{"time":0.9333,"name":"lizi_28"},{"time":0.9666,"name":"lizi_29"}]},"lizi5":{"attachment":[{"time":0,"name":"lizi_00"},{"time":0.0333,"name":"lizi_01"},{"time":0.0666,"name":"lizi_02"},{"time":0.1,"name":"lizi_03"},{"time":0.1333,"name":"lizi_04"},{"time":0.1666,"name":"lizi_05"},{"time":0.2,"name":"lizi_06"},{"time":0.2333,"name":"lizi_07"},{"time":0.2666,"name":"lizi_08"},{"time":0.3,"name":"lizi_09"},{"time":0.3333,"name":"lizi_10"},{"time":0.3666,"name":"lizi_11"},{"time":0.4,"name":"lizi_12"},{"time":0.4333,"name":"lizi_13"},{"time":0.4666,"name":"lizi_14"},{"time":0.5,"name":"lizi_15"},{"time":0.5333,"name":"lizi_16"},{"time":0.5666,"name":"lizi_17"},{"time":0.6,"name":"lizi_18"},{"time":0.6333,"name":"lizi_19"},{"time":0.6666,"name":"lizi_20"},{"time":0.7,"name":"lizi_21"},{"time":0.7333,"name":"lizi_22"},{"time":0.7666,"name":"lizi_23"},{"time":0.8,"name":"lizi_24"},{"time":0.8333,"name":"lizi_25"},{"time":0.8666,"name":"lizi_26"},{"time":0.9,"name":"lizi_27"},{"time":0.9333,"name":"lizi_28"},{"time":0.9666,"name":"lizi_29"}]},"lizi6":{"attachment":[{"time":0,"name":"lizi_00"},{"time":0.0333,"name":"lizi_01"},{"time":0.0666,"name":"lizi_02"},{"time":0.1,"name":"lizi_03"},{"time":0.1333,"name":"lizi_04"},{"time":0.1666,"name":"lizi_05"},{"time":0.2,"name":"lizi_06"},{"time":0.2333,"name":"lizi_07"},{"time":0.2666,"name":"lizi_08"},{"time":0.3,"name":"lizi_09"},{"time":0.3333,"name":"lizi_10"},{"time":0.3666,"name":"lizi_11"},{"time":0.4,"name":"lizi_12"},{"time":0.4333,"name":"lizi_13"},{"time":0.4666,"name":"lizi_14"},{"time":0.5,"name":"lizi_15"},{"time":0.5333,"name":"lizi_16"},{"time":0.5666,"name":"lizi_17"},{"time":0.6,"name":"lizi_18"},{"time":0.6333,"name":"lizi_19"},{"time":0.6666,"name":"lizi_20"},{"time":0.7,"name":"lizi_21"},{"time":0.7333,"name":"lizi_22"},{"time":0.7666,"name":"lizi_23"},{"time":0.8,"name":"lizi_24"},{"time":0.8333,"name":"lizi_25"},{"time":0.8666,"name":"lizi_26"},{"time":0.9,"name":"lizi_27"},{"time":0.9333,"name":"lizi_28"},{"time":0.9666,"name":"lizi_29"}]},"lizi7":{"attachment":[{"time":0,"name":"lizi_00"},{"time":0.0333,"name":"lizi_01"},{"time":0.0666,"name":"lizi_02"},{"time":0.1,"name":"lizi_03"},{"time":0.1333,"name":"lizi_04"},{"time":0.1666,"name":"lizi_05"},{"time":0.2,"name":"lizi_06"},{"time":0.2333,"name":"lizi_07"},{"time":0.2666,"name":"lizi_08"},{"time":0.3,"name":"lizi_09"},{"time":0.3333,"name":"lizi_10"},{"time":0.3666,"name":"lizi_11"},{"time":0.4,"name":"lizi_12"},{"time":0.4333,"name":"lizi_13"},{"time":0.4666,"name":"lizi_14"},{"time":0.5,"name":"lizi_15"},{"time":0.5333,"name":"lizi_16"},{"time":0.5666,"name":"lizi_17"},{"time":0.6,"name":"lizi_18"},{"time":0.6333,"name":"lizi_19"},{"time":0.6666,"name":"lizi_20"},{"time":0.7,"name":"lizi_21"},{"time":0.7333,"name":"lizi_22"},{"time":0.7666,"name":"lizi_23"},{"time":0.8,"name":"lizi_24"},{"time":0.8333,"name":"lizi_25"},{"time":0.8666,"name":"lizi_26"},{"time":0.9,"name":"lizi_27"},{"time":0.9333,"name":"lizi_28"},{"time":0.9666,"name":"lizi_29"}]},"lizi8":{"attachment":[{"time":0,"name":"lizi_00"},{"time":0.0333,"name":"lizi_01"},{"time":0.0666,"name":"lizi_02"},{"time":0.1,"name":"lizi_03"},{"time":0.1333,"name":"lizi_04"},{"time":0.1666,"name":"lizi_05"},{"time":0.2,"name":"lizi_06"},{"time":0.2333,"name":"lizi_07"},{"time":0.2666,"name":"lizi_08"},{"time":0.3,"name":"lizi_09"},{"time":0.3333,"name":"lizi_10"},{"time":0.3666,"name":"lizi_11"},{"time":0.4,"name":"lizi_12"},{"time":0.4333,"name":"lizi_13"},{"time":0.4666,"name":"lizi_14"},{"time":0.5,"name":"lizi_15"},{"time":0.5333,"name":"lizi_16"},{"time":0.5666,"name":"lizi_17"},{"time":0.6,"name":"lizi_18"},{"time":0.6333,"name":"lizi_19"},{"time":0.6666,"name":"lizi_20"},{"time":0.7,"name":"lizi_21"},{"time":0.7333,"name":"lizi_22"},{"time":0.7666,"name":"lizi_23"},{"time":0.8,"name":"lizi_24"},{"time":0.8333,"name":"lizi_25"},{"time":0.8666,"name":"lizi_26"},{"time":0.9,"name":"lizi_27"},{"time":0.9333,"name":"lizi_28"},{"time":0.9666,"name":"lizi_29"}]},"lizi9":{"attachment":[{"time":0,"name":"lizi_00"},{"time":0.0333,"name":"lizi_01"},{"time":0.0666,"name":"lizi_02"},{"time":0.1,"name":"lizi_03"},{"time":0.1333,"name":"lizi_04"},{"time":0.1666,"name":"lizi_05"},{"time":0.2,"name":"lizi_06"},{"time":0.2333,"name":"lizi_07"},{"time":0.2666,"name":"lizi_08"},{"time":0.3,"name":"lizi_09"},{"time":0.3333,"name":"lizi_10"},{"time":0.3666,"name":"lizi_11"},{"time":0.4,"name":"lizi_12"},{"time":0.4333,"name":"lizi_13"},{"time":0.4666,"name":"lizi_14"},{"time":0.5,"name":"lizi_15"},{"time":0.5333,"name":"lizi_16"},{"time":0.5666,"name":"lizi_17"},{"time":0.6,"name":"lizi_18"},{"time":0.6333,"name":"lizi_19"},{"time":0.6666,"name":"lizi_20"},{"time":0.7,"name":"lizi_21"},{"time":0.7333,"name":"lizi_22"},{"time":0.7666,"name":"lizi_23"},{"time":0.8,"name":"lizi_24"},{"time":0.8333,"name":"lizi_25"},{"time":0.8666,"name":"lizi_26"},{"time":0.9,"name":"lizi_27"},{"time":0.9333,"name":"lizi_28"},{"time":0.9666,"name":"lizi_29"}]},"lizi10":{"attachment":[{"time":0,"name":"lizi_00"},{"time":0.0333,"name":"lizi_01"},{"time":0.0666,"name":"lizi_02"},{"time":0.1,"name":"lizi_03"},{"time":0.1333,"name":"lizi_04"},{"time":0.1666,"name":"lizi_05"},{"time":0.2,"name":"lizi_06"},{"time":0.2333,"name":"lizi_07"},{"time":0.2666,"name":"lizi_08"},{"time":0.3,"name":"lizi_09"},{"time":0.3333,"name":"lizi_10"},{"time":0.3666,"name":"lizi_11"},{"time":0.4,"name":"lizi_12"},{"time":0.4333,"name":"lizi_13"},{"time":0.4666,"name":"lizi_14"},{"time":0.5,"name":"lizi_15"},{"time":0.5333,"name":"lizi_16"},{"time":0.5666,"name":"lizi_17"},{"time":0.6,"name":"lizi_18"},{"time":0.6333,"name":"lizi_19"},{"time":0.6666,"name":"lizi_20"},{"time":0.7,"name":"lizi_21"},{"time":0.7333,"name":"lizi_22"},{"time":0.7666,"name":"lizi_23"},{"time":0.8,"name":"lizi_24"},{"time":0.8333,"name":"lizi_25"},{"time":0.8666,"name":"lizi_26"},{"time":0.9,"name":"lizi_27"},{"time":0.9333,"name":"lizi_28"},{"time":0.9666,"name":"lizi_29"}]},"lizi11":{"attachment":[{"time":0,"name":"lizi_00"},{"time":0.0333,"name":"lizi_01"},{"time":0.0666,"name":"lizi_02"},{"time":0.1,"name":"lizi_03"},{"time":0.1333,"name":"lizi_04"},{"time":0.1666,"name":"lizi_05"},{"time":0.2,"name":"lizi_06"},{"time":0.2333,"name":"lizi_07"},{"time":0.2666,"name":"lizi_08"},{"time":0.3,"name":"lizi_09"},{"time":0.3333,"name":"lizi_10"},{"time":0.3666,"name":"lizi_11"},{"time":0.4,"name":"lizi_12"},{"time":0.4333,"name":"lizi_13"},{"time":0.4666,"name":"lizi_14"},{"time":0.5,"name":"lizi_15"},{"time":0.5333,"name":"lizi_16"},{"time":0.5666,"name":"lizi_17"},{"time":0.6,"name":"lizi_18"},{"time":0.6333,"name":"lizi_19"},{"time":0.6666,"name":"lizi_20"},{"time":0.7,"name":"lizi_21"},{"time":0.7333,"name":"lizi_22"},{"time":0.7666,"name":"lizi_23"},{"time":0.8,"name":"lizi_24"},{"time":0.8333,"name":"lizi_25"},{"time":0.8666,"name":"lizi_26"},{"time":0.9,"name":"lizi_27"},{"time":0.9333,"name":"lizi_28"},{"time":0.9666,"name":"lizi_29"}]},"lizi12":{"attachment":[{"time":0,"name":"lizi_00"},{"time":0.0333,"name":"lizi_01"},{"time":0.0666,"name":"lizi_02"},{"time":0.1,"name":"lizi_03"},{"time":0.1333,"name":"lizi_04"},{"time":0.1666,"name":"lizi_05"},{"time":0.2,"name":"lizi_06"},{"time":0.2333,"name":"lizi_07"},{"time":0.2666,"name":"lizi_08"},{"time":0.3,"name":"lizi_09"},{"time":0.3333,"name":"lizi_10"},{"time":0.3666,"name":"lizi_11"},{"time":0.4,"name":"lizi_12"},{"time":0.4333,"name":"lizi_13"},{"time":0.4666,"name":"lizi_14"},{"time":0.5,"name":"lizi_15"},{"time":0.5333,"name":"lizi_16"},{"time":0.5666,"name":"lizi_17"},{"time":0.6,"name":"lizi_18"},{"time":0.6333,"name":"lizi_19"},{"time":0.6666,"name":"lizi_20"},{"time":0.7,"name":"lizi_21"},{"time":0.7333,"name":"lizi_22"},{"time":0.7666,"name":"lizi_23"},{"time":0.8,"name":"lizi_24"},{"time":0.8333,"name":"lizi_25"},{"time":0.8666,"name":"lizi_26"},{"time":0.9,"name":"lizi_27"},{"time":0.9333,"name":"lizi_28"},{"time":0.9666,"name":"lizi_29"}]},"lizi13":{"attachment":[{"time":0,"name":"lizi_00"},{"time":0.0333,"name":"lizi_01"},{"time":0.0666,"name":"lizi_02"},{"time":0.1,"name":"lizi_03"},{"time":0.1333,"name":"lizi_04"},{"time":0.1666,"name":"lizi_05"},{"time":0.2,"name":"lizi_06"},{"time":0.2333,"name":"lizi_07"},{"time":0.2666,"name":"lizi_08"},{"time":0.3,"name":"lizi_09"},{"time":0.3333,"name":"lizi_10"},{"time":0.3666,"name":"lizi_11"},{"time":0.4,"name":"lizi_12"},{"time":0.4333,"name":"lizi_13"},{"time":0.4666,"name":"lizi_14"},{"time":0.5,"name":"lizi_15"},{"time":0.5333,"name":"lizi_16"},{"time":0.5666,"name":"lizi_17"},{"time":0.6,"name":"lizi_18"},{"time":0.6333,"name":"lizi_19"},{"time":0.6666,"name":"lizi_20"},{"time":0.7,"name":"lizi_21"},{"time":0.7333,"name":"lizi_22"},{"time":0.7666,"name":"lizi_23"},{"time":0.8,"name":"lizi_24"},{"time":0.8333,"name":"lizi_25"},{"time":0.8666,"name":"lizi_26"},{"time":0.9,"name":"lizi_27"},{"time":0.9333,"name":"lizi_28"},{"time":0.9666,"name":"lizi_29"}]},"lizi14":{"attachment":[{"time":0,"name":"lizi_00"},{"time":0.0333,"name":"lizi_01"},{"time":0.0666,"name":"lizi_02"},{"time":0.1,"name":"lizi_03"},{"time":0.1333,"name":"lizi_04"},{"time":0.1666,"name":"lizi_05"},{"time":0.2,"name":"lizi_06"},{"time":0.2333,"name":"lizi_07"},{"time":0.2666,"name":"lizi_08"},{"time":0.3,"name":"lizi_09"},{"time":0.3333,"name":"lizi_10"},{"time":0.3666,"name":"lizi_11"},{"time":0.4,"name":"lizi_12"},{"time":0.4333,"name":"lizi_13"},{"time":0.4666,"name":"lizi_14"},{"time":0.5,"name":"lizi_15"},{"time":0.5333,"name":"lizi_16"},{"time":0.5666,"name":"lizi_17"},{"time":0.6,"name":"lizi_18"},{"time":0.6333,"name":"lizi_19"},{"time":0.6666,"name":"lizi_20"},{"time":0.7,"name":"lizi_21"},{"time":0.7333,"name":"lizi_22"},{"time":0.7666,"name":"lizi_23"},{"time":0.8,"name":"lizi_24"},{"time":0.8333,"name":"lizi_25"},{"time":0.8666,"name":"lizi_26"},{"time":0.9,"name":"lizi_27"},{"time":0.9333,"name":"lizi_28"},{"time":0.9666,"name":"lizi_29"}]},"lizi15":{"attachment":[{"time":0,"name":"lizi_00"},{"time":0.0333,"name":"lizi_01"},{"time":0.0666,"name":"lizi_02"},{"time":0.1,"name":"lizi_03"},{"time":0.1333,"name":"lizi_04"},{"time":0.1666,"name":"lizi_05"},{"time":0.2,"name":"lizi_06"},{"time":0.2333,"name":"lizi_07"},{"time":0.2666,"name":"lizi_08"},{"time":0.3,"name":"lizi_09"},{"time":0.3333,"name":"lizi_10"},{"time":0.3666,"name":"lizi_11"},{"time":0.4,"name":"lizi_12"},{"time":0.4333,"name":"lizi_13"},{"time":0.4666,"name":"lizi_14"},{"time":0.5,"name":"lizi_15"},{"time":0.5333,"name":"lizi_16"},{"time":0.5666,"name":"lizi_17"},{"time":0.6,"name":"lizi_18"},{"time":0.6333,"name":"lizi_19"},{"time":0.6666,"name":"lizi_20"},{"time":0.7,"name":"lizi_21"},{"time":0.7333,"name":"lizi_22"},{"time":0.7666,"name":"lizi_23"},{"time":0.8,"name":"lizi_24"},{"time":0.8333,"name":"lizi_25"},{"time":0.8666,"name":"lizi_26"},{"time":0.9,"name":"lizi_27"},{"time":0.9333,"name":"lizi_28"},{"time":0.9666,"name":"lizi_29"}]},"lizi16":{"attachment":[{"time":0,"name":"lizi_00"},{"time":0.0333,"name":"lizi_01"},{"time":0.0666,"name":"lizi_02"},{"time":0.1,"name":"lizi_03"},{"time":0.1333,"name":"lizi_04"},{"time":0.1666,"name":"lizi_05"},{"time":0.2,"name":"lizi_06"},{"time":0.2333,"name":"lizi_07"},{"time":0.2666,"name":"lizi_08"},{"time":0.3,"name":"lizi_09"},{"time":0.3333,"name":"lizi_10"},{"time":0.3666,"name":"lizi_11"},{"time":0.4,"name":"lizi_12"},{"time":0.4333,"name":"lizi_13"},{"time":0.4666,"name":"lizi_14"},{"time":0.5,"name":"lizi_15"},{"time":0.5333,"name":"lizi_16"},{"time":0.5666,"name":"lizi_17"},{"time":0.6,"name":"lizi_18"},{"time":0.6333,"name":"lizi_19"},{"time":0.6666,"name":"lizi_20"},{"time":0.7,"name":"lizi_21"},{"time":0.7333,"name":"lizi_22"},{"time":0.7666,"name":"lizi_23"},{"time":0.8,"name":"lizi_24"},{"time":0.8333,"name":"lizi_25"},{"time":0.8666,"name":"lizi_26"},{"time":0.9,"name":"lizi_27"},{"time":0.9333,"name":"lizi_28"},{"time":0.9666,"name":"lizi_29"}]}},"bones":{"bone":{"translate":[{"time":0,"x":0,"y":0,"curve":"stepped"},{"time":1,"x":0,"y":0}]}}}}}